databallpy/__init__.py
databallpy/base_logging_config.ini
databallpy/data_parsers/__init__.py
databallpy/data_parsers/event_data_parsers/__init__.py
databallpy/data_parsers/event_data_parsers/instat_parser.py
databallpy/data_parsers/event_data_parsers/metrica_event_data_parser.py
databallpy/data_parsers/event_data_parsers/opta_parser.py
databallpy/data_parsers/event_data_parsers/scisports_parser.py
databallpy/data_parsers/event_data_parsers/sportec_parser.py
databallpy/data_parsers/event_data_parsers/statsbomb_parser.py
databallpy/data_parsers/event_data_parsers/utils/__init__.py
databallpy/data_parsers/event_data_parsers/utils/_normalize_playing_direction_events.py
databallpy/data_parsers/kloppy_parsers/__init__.py
databallpy/data_parsers/kloppy_parsers/helpers.py
databallpy/data_parsers/metadata.py
databallpy/data_parsers/metrica_metadata_parser.py
databallpy/data_parsers/sportec_metadata_parser.py
databallpy/data_parsers/tracking_data_parsers/__init__.py
databallpy/data_parsers/tracking_data_parsers/inmotio_parser.py
databallpy/data_parsers/tracking_data_parsers/metrica_tracking_data_parser.py
databallpy/data_parsers/tracking_data_parsers/tracab_parser.py
databallpy/data_parsers/tracking_data_parsers/utils/__init__.py
databallpy/data_parsers/tracking_data_parsers/utils/_add_ball_data_to_dict.py
databallpy/data_parsers/tracking_data_parsers/utils/_add_datetime.py
databallpy/data_parsers/tracking_data_parsers/utils/_add_periods_to_tracking_data.py
databallpy/data_parsers/tracking_data_parsers/utils/_add_player_tracking_data_to_dict.py
databallpy/data_parsers/tracking_data_parsers/utils/_adjust_start_end_frames.py
databallpy/data_parsers/tracking_data_parsers/utils/_get_gametime.py
databallpy/data_parsers/tracking_data_parsers/utils/_insert_missing_rows.py
databallpy/data_parsers/tracking_data_parsers/utils/_normalize_playing_direction_tracking.py
databallpy/data_parsers/tracking_data_parsers/utils/_quality_check_tracking_data.py
databallpy/events/__init__.py
databallpy-0.7.2.dist-info/METADATA
databallpy-0.7.2.dist-info/WHEEL
databallpy-0.7.2.dist-info/licenses/LICENSE
databallpy-0.7.2.dist-info/RECORD
