Metadata-Version: 2.4
Name: databallpy
Version: 0.7.2
Summary: A package for loading, preprocessing, vizualising and synchronizing soccere event and tracking data.
License: MIT
License-File: LICENSE
Keywords: soccer,football,tracking data,event data
Author: Alexander Oonk
Author-email: alexanderoonk26@gmail.com
Maintainer: Alexander Oonk
Maintainer-email: alexanderoonk26@gmail.com
Requires-Python: >=3.10,<3.14
Classifier: Intended Audience :: Developers
Classifier: Intended Audience :: Science/Research
Classifier: License :: OSI Approved :: MIT License
Classifier: Programming Language :: Python :: 3
Classifier: Programming Language :: Python :: 3.10
Classifier: Programming Language :: Python :: 3.11
Classifier: Programming Language :: Python :: 3.12
Classifier: Programming Language :: Python :: 3.13
Classifier: Topic :: Scientific/Engineering
Provides-Extra: accessible-space
Provides-Extra: kloppy
Requires-Dist: accessible-space (>=2.0.13) ; extra == "accessible-space"
Requires-Dist: beautifulsoup4 (>=4.11.1,<5.0.0)
Requires-Dist: chardet (>=5.2.0,<6.0.0)
Requires-Dist: kloppy (>=3.18.0) ; extra == "kloppy"
Requires-Dist: lxml (>=4.9,<=6.0)
Requires-Dist: matplotlib (>=3.6.3,<4.0.0)
Requires-Dist: numpy (>=2.1,<3.0)
Requires-Dist: pandas (>=2.1,<3.0)
Requires-Dist: pandera (>=0.22.1,<0.23.0)
Requires-Dist: pyarrow (>=19.0.0,<20.0.0)
Requires-Dist: requests (>=2.31,<3.0)
Requires-Dist: scipy (>=1.11,<2.0)
Requires-Dist: tqdm (>=4.64.1,<5.0.0)
Project-URL: Documentation, https://github.com/Alek050/databallpy/tree/main/docs
Project-URL: Homepage, https://pypi.org/project/databallpy/
Project-URL: Repository, https://github.com/Alek050/databallpy
